frykit_data/__init__.py
frykit_data/data/NEO_modis_aer_od.csv
frykit_data/data/china/amap/cn_border.bin
frykit_data/data/china/amap/cn_city.bin
frykit_data/data/china/amap/cn_city.csv
frykit_data/data/china/amap/cn_district.bin
frykit_data/data/china/amap/cn_district.csv
frykit_data/data/china/amap/cn_province.bin
frykit_data/data/china/amap/cn_province.csv
frykit_data/data/china/cn_line.bin
frykit_data/data/china/tianditu/cn_border.bin
frykit_data/data/china/tianditu/cn_city.bin
frykit_data/data/china/tianditu/cn_city.csv
frykit_data/data/china/tianditu/cn_district.bin
frykit_data/data/china/tianditu/cn_district.csv
frykit_data/data/china/tianditu/cn_province.bin
frykit_data/data/china/tianditu/cn_province.csv
frykit_data/data/test.npz
frykit_data/data/world/country.bin
frykit_data/data/world/land.bin
frykit_data/data/world/ocean.bin
frykit_data/data/zh_font.otf
frykit_data/py.typed
frykit_data-0.1.0.dist-info/licenses/LICENSE
frykit_data-0.1.0.dist-info/WHEEL
frykit_data-0.1.0.dist-info/METADATA
frykit_data-0.1.0.dist-info/RECORD
