Metadata-Version: 2.4
Name: frykit_data
Version: 0.1.0
Summary: Data for frykit
Author: ZhaJiMan
Author-email: ZhaJiMan <915023793@qq.com>
License-Expression: MIT
License-File: LICENSE
Classifier: Programming Language :: Python :: 3
Classifier: Operating System :: OS Independent
Classifier: License :: OSI Approved :: MIT License
Requires-Python: >=3.10
Project-URL: Homepage, https://github.com/ZhaJiMan/frykit_data
Project-URL: Issues, https://github.com/ZhaJiMan/frykit_data/issues
